pcairo/__init__.py
pcairo/cairoP.py
pcairo/hueToRgb.py
pcairo/__pycache__/cairoP.cpython-39.pyc
CairoPLib-0.0.5.dist-info/METADATA
CairoPLib-0.0.5.dist-info/WHEEL
CairoPLib-0.0.5.dist-info/top_level.txt
CairoPLib-0.0.5.dist-info/RECORD
